shinylive/__init__.py
shinylive/_app_json.py
shinylive/_assets.py
shinylive/_deps.py
shinylive/_export.py
shinylive/_main.py
shinylive/_url.py
shinylive/_utils.py
shinylive/py.typed
shinylive/_version/__init__.py
shinylive-0.8.5.dist-info/licenses/LICENSE
shinylive-0.8.5.dist-info/METADATA
shinylive-0.8.5.dist-info/WHEEL
shinylive-0.8.5.dist-info/entry_points.txt
shinylive-0.8.5.dist-info/top_level.txt
shinylive-0.8.5.dist-info/RECORD
