Metadata-Version: 2.4
Name: shinylive
Version: 0.8.5
Summary: Run Shiny applications running Python in the browser.
Home-page: https://github.com/posit-dev/py-shinylive
Author: Winston Chang
Author-email: winston@posit.co
License: MIT
Project-URL: Bug Tracker, https://github.com/posit-dev/py-shinylive/issues
Project-URL: Documentation, https://github.com/posit-dev/py-shinylive
Project-URL: Source Code, https://github.com/posit-dev/py-shinylive
Platform: any
Classifier: Development Status :: 2 - Pre-Alpha
Classifier: Intended Audience :: Developers
Classifier: License :: OSI Approved :: MIT License
Classifier: Natural Language :: English
Classifier: Programming Language :: Python :: 3.8
Classifier: Programming Language :: Python :: 3.9
Classifier: Programming Language :: Python :: 3.10
Classifier: Programming Language :: Python :: 3.11
Classifier: Programming Language :: Python :: 3.12
Requires-Python: >=3.8
License-File: LICENSE
Requires-Dist: shiny
Requires-Dist: click>=8.1.7
Requires-Dist: appdirs>=1.4.4
Requires-Dist: lzstring>=1.0.4
Requires-Dist: typing-extensions>=4.0.1
Requires-Dist: setuptools; python_version >= "3.12"
Requires-Dist: chevron>=0.14.0
Provides-Extra: test
Requires-Dist: pytest>=6.2.4; extra == "test"
Provides-Extra: dev
Requires-Dist: black>=22.3.0; extra == "dev"
Requires-Dist: flake8>=3.9.2; extra == "dev"
Requires-Dist: flake8-bugbear>=22.6.22; extra == "dev"
Requires-Dist: isort>=5.11.2; extra == "dev"
Requires-Dist: pyright>=1.1.284; extra == "dev"
Requires-Dist: wheel; extra == "dev"
Dynamic: license-file
